MANIFEST.in
README.md
setup.cfg
setup.py
loadimpact_cli.egg-info/PKG-INFO
loadimpact_cli.egg-info/SOURCES.txt
loadimpact_cli.egg-info/dependency_links.txt
loadimpact_cli.egg-info/entry_points.txt
loadimpact_cli.egg-info/requires.txt
loadimpact_cli.egg-info/top_level.txt
loadimpactcli/__init__.py
loadimpactcli/client.py
loadimpactcli/config.py
loadimpactcli/datastore_commands.py
loadimpactcli/errors.py
loadimpactcli/loadimpact_cli.py
loadimpactcli/metric_commands.py
loadimpactcli/organization_commands.py
loadimpactcli/test_commands.py
loadimpactcli/userscenario_commands.py
loadimpactcli/util.py
loadimpactcli/version.py