Metadata-Version: 1.0
Name: loadimpact-cli
Version: 1.1.1
Summary: The Load Impact CLI interfaces with Load Impact's cloud-based performance testing platform
Home-page: http://developers.loadimpact.com/
Author: Load Impact
Author-email: support@loadimpact.com
License: LICENSE.txt
Platform: UNKNOWN
